wgman1ton/__init__.py
wgman1ton/cli_script.py
wgman1ton/main.py
wgman1ton-0.4.0.dist-info/LICENSE
wgman1ton-0.4.0.dist-info/METADATA
wgman1ton-0.4.0.dist-info/WHEEL
wgman1ton-0.4.0.dist-info/entry_points.txt
wgman1ton-0.4.0.dist-info/top_level.txt
wgman1ton-0.4.0.dist-info/RECORD
