Metadata-Version: 2.1
Name: wgman1ton
Version: 0.4.0
Summary: Simple cli-tool to create the wg0.conf-files for a 1-to-many network infrastructure in which the N-peers can connect to each other via the 1-peer.
Home-page: https://codeberg.org/hanser/1toN-wireguard-manager
Author: Johannes Stefan
Author-email: message@johannesstefan.de
Project-URL: Bug Tracker, https://codeberg.org/hanser/1toN-wireguard-manager/issues
Classifier: Programming Language :: Python :: 3
Classifier: Operating System :: OS Independent
Classifier: Intended Audience :: Developers
Requires-Python: >=3.6
License-File: LICENSE
Requires-Dist: qrcode
Requires-Dist: cli-ui
Requires-Dist: darkdetect
